oscar_stripe_sca/__init__.py
oscar_stripe_sca/apps.py
oscar_stripe_sca/facade.py
oscar_stripe_sca/forms.py
oscar_stripe_sca/models.py
oscar_stripe_sca/settings.py
oscar_stripe_sca/tests.py
oscar_stripe_sca/views.py
oscar_stripe_sca/.idea/.gitignore
oscar_stripe_sca/.idea/encodings.xml
oscar_stripe_sca/.idea/misc.xml
oscar_stripe_sca/.idea/modules.xml
oscar_stripe_sca/.idea/oscar_stripe_sca.iml
oscar_stripe_sca/.idea/vcs.xml
oscar_stripe_sca/.idea/workspace.xml
oscar_stripe_sca/.idea/inspectionProfiles/Project_Default.xml
oscar_stripe_sca/.idea/inspectionProfiles/profiles_settings.xml
oscar_stripe_sca/templates/oscar_stripe_sca/stripe_payment_details.html
oscar_stripe_sca/templates/oscar_stripe_sca/stripe_preview.html
django_oscar_stripe_sca-0.8.2.dist-info/licenses/LICENSE
django_oscar_stripe_sca-0.8.2.dist-info/WHEEL
django_oscar_stripe_sca-0.8.2.dist-info/METADATA
django_oscar_stripe_sca-0.8.2.dist-info/RECORD
