Metadata-Version: 2.4
Name: django-oscar-stripe-sca
Version: 0.8.2
Summary: Stripe Checkout (with Payment Intents) payment module for django-oscar
Keywords: Payment,Stripe
Author-email: Steve Bradshaw <steve@pcfive.co.uk>
Classifier: Development Status :: 4 - Beta
Classifier: Environment :: Web Environment
Classifier: Framework :: Django
Classifier: Intended Audience :: Developers
Classifier: License :: OSI Approved :: MIT License
Classifier: Programming Language :: Python :: 3 :: Only
License-File: LICENSE
Requires-Dist: django>=3.2
Requires-Dist: django-oscar>=2
Requires-Dist: stripe>=2.27.0
Project-URL: Homepage, https://github.com/st8st8/django-oscar-stripe-sca
